datrics/__init__.py
datrics/__main__.py
datrics/constants/__init__.py
datrics/constants/links.py
datrics/constants/pathes.py
datrics/controllers/__init__.py
datrics/controllers/auth_controller.py
datrics/controllers/brick_controller.py
datrics/controllers/projects_controller.py
datrics/services/__init__.py
datrics/services/brick_service.py
datrics/services/show_data_service.py
datrics/services/show_message.py
datrics/services/storage_service.py
datrics/services/template_brick/cookiecutter.json
datrics/services/template_brick/{{cookiecutter.brick_directory_name}}/brick_custom_code.py
datrics/services/template_brick/{{cookiecutter.brick_directory_name}}/manifest.yml
datrics-0.0.4.dist-info/METADATA
datrics-0.0.4.dist-info/WHEEL
datrics-0.0.4.dist-info/dependency_links.txt
datrics-0.0.4.dist-info/entry_points.txt
datrics-0.0.4.dist-info/top_level.txt
datrics-0.0.4.dist-info/RECORD
