Metadata-Version: 2.1
Name: datrics
Version: 0.0.4
Summary: CLI for datrics.ai platform that allows you to create and manage custom bricks
Home-page: https://github.com/datrics-ai/datrics-cli
Author: Roman Malkevych
Author-email: rm@datrics.ai
License: MIT
Platform: UNKNOWN
Classifier: License :: OSI Approved :: MIT License
Classifier: Programming Language :: Python :: 2.7
Classifier: Programming Language :: Python :: 3
Classifier: Programming Language :: Python :: 3.7
Requires-Python: >=2.7
Requires-Dist: requests (==v2.26.0)
Requires-Dist: click (==7.1.2)
Requires-Dist: cookiecutter (==1.7.2)
